pcapcli/__init__.py
pcapcli/exceptions.py
personalcapital_cli-1.0.6.dist-info/LICENSE.txt
personalcapital_cli-1.0.6.dist-info/METADATA
personalcapital_cli-1.0.6.dist-info/WHEEL
personalcapital_cli-1.0.6.dist-info/entry_points.txt
personalcapital_cli-1.0.6.dist-info/top_level.txt
personalcapital_cli-1.0.6.dist-info/RECORD
