Metadata-Version: 2.1
Name: personalcapital-cli
Version: 1.0.6
Summary: Personal Capital CLI
Home-page: https://github.com/clintecker/personalcapital-cli
Author: Clint Ecker
Author-email: me@clintecker.com
License: MIT
Platform: UNKNOWN
Requires-Python: >=3.7
Requires-Dist: python-clint-utilities (==1.2.1)
Requires-Dist: requests
Requires-Dist: rich
Requires-Dist: google-api-python-client
Requires-Dist: google-auth-httplib2
Requires-Dist: google-auth-oauthlib
Provides-Extra: test
Requires-Dist: responses ; extra == 'test'
Requires-Dist: tox ; extra == 'test'
Requires-Dist: pytest ; extra == 'test'
Requires-Dist: pytest-cov ; extra == 'test'
Requires-Dist: mypy ; extra == 'test'
Requires-Dist: flake8 (>=3.3.0) ; extra == 'test'
Requires-Dist: pep8-naming (>=0.4.1) ; extra == 'test'
Requires-Dist: flake8-quotes (>=0.8.1) ; extra == 'test'
Requires-Dist: flake8-import-order (>=0.9.0) ; extra == 'test'
Requires-Dist: Sphinx ; extra == 'test'
Requires-Dist: wheel ; extra == 'test'
Requires-Dist: black ; extra == 'test'
Requires-Dist: isort ; extra == 'test'
